lambda_parse_sqs/__init__.py
lambda_parse_sqs/parse_sqs.py
lambda_parse_sqs/sqs_message_parser.py
lambda_parse_sqs/utils.py
lambda_parse_sqs/errors/__init__.py
lambda_parse_sqs/errors/provider_selection_error.py
lambda_parse_sqs/errors/records_not_found_error.py
lambda_parse_sqs-0.2.2.dist-info/LICENSE
lambda_parse_sqs-0.2.2.dist-info/METADATA
lambda_parse_sqs-0.2.2.dist-info/WHEEL
lambda_parse_sqs-0.2.2.dist-info/top_level.txt
lambda_parse_sqs-0.2.2.dist-info/RECORD
