Metadata-Version: 2.1
Name: lambda-parse-sqs
Version: 0.2.2
Summary: Parse SQS messages from lambda triggered SQS subscription
Home-page: https://github.com/msantino/lambda-parse-sqs
Author: Marcelo Santino
Author-email: eu@marcelosantino.com.br
License: UNKNOWN
Platform: UNKNOWN
Classifier: Programming Language :: Python :: 3
Classifier: License :: OSI Approved :: MIT License
Classifier: Operating System :: OS Independent
